{"models":{"dedicated.nasha.Access":{"namespace":"dedicated.nasha","id":"Access","description":"Define Acl for partition","properties":{"ip":{"fullType":"ipBlock","canBeNull":0,"type":"ipBlock","description":"the ip in root on storage","readOnly":1},"accessId":{"fullType":"long","canBeNull":0,"type":"long","description":"the id of the access","readOnly":1}}},"dedicated.nasha.Partition":{"namespace":"dedicated.nasha","id":"Partition","description":"Storage zpool partition","properties":{"protocol":{"fullType":"dedicated.storage.ProtocolEnum","canBeNull":0,"type":"dedicated.storage.ProtocolEnum","description":"must be nfs cifs or both","readOnly":1},"partitionName":{"fullType":"string","canBeNull":0,"type":"string","description":"the given name of partition","readOnly":1},"size":{"fullType":"long","canBeNull":0,"type":"long","description":"Partition size","readOnly":0}}},"dedicated.storage.SnapshotEnum":{"namespace":"dedicated.storage","enum":["day-1","day-2","day-3","day-7","hour-1","hour-6"],"id":"SnapshotEnum","enumType":"string","description":"Partition snapshot allowed "},"dedicated.nasha.Storage":{"namespace":"dedicated.nasha","id":"Storage","description":"Storage nas HA","properties":{"datacenter":{"fullType":"string","canBeNull":1,"type":"string","description":"area of nas","readOnly":1},"canCreatePartition":{"fullType":"boolean","canBeNull":0,"type":"boolean","description":"True, if partition creation is allowed on this nas HA","readOnly":1},"monitored":{"fullType":"boolean","canBeNull":0,"type":"boolean","description":"Send an email to customer if any issue is detected","readOnly":0},"zpoolCapacity":{"fullType":"long","canBeNull":0,"type":"long","description":"percentage of nas space used in %","readOnly":1},"ip":{"fullType":"ip","canBeNull":1,"type":"ip","description":"Access ip of nas","readOnly":1},"serviceName":{"fullType":"string","canBeNull":0,"type":"string","description":"The storage service name","readOnly":1},"customName":{"fullType":"string","canBeNull":1,"type":"string","description":"The name you give to the nas","readOnly":0},"zpoolSize":{"fullType":"long","canBeNull":0,"type":"long","description":"the size of the nas","readOnly":1}}},"dedicated.storage.ProtocolEnum":{"namespace":"dedicated.storage","enum":["CIFS","NFS","NFS_CIFS"],"id":"ProtocolEnum","enumType":"string","description":"Partition Protocol"},"dedicated.nasTask.Task":{"namespace":"dedicated.nasTask","id":"Task","description":"Storage task","properties":{"taskId":{"fullType":"long","canBeNull":0,"type":"long","description":"id of the task","readOnly":1},"storageName":{"fullType":"string","canBeNull":1,"type":"string","description":"the name of your service","readOnly":1},"status":{"fullType":"dedicated.TaskStatusEnum","canBeNull":0,"type":"dedicated.TaskStatusEnum","description":"The actual state of the task","readOnly":1},"details":{"fullType":"string","canBeNull":1,"type":"string","description":"information about operation","readOnly":1},"lastUpdate":{"fullType":"datetime","canBeNull":1,"type":"datetime","description":"last modification of task","readOnly":1},"todoDate":{"fullType":"datetime","canBeNull":1,"type":"datetime","description":"Insertion of task in the todo","readOnly":1},"operation":{"fullType":"dedicated.storage.TaskFunctionEnum","canBeNull":0,"type":"dedicated.storage.TaskFunctionEnum","description":"Task type of operation","readOnly":1},"doneDate":{"fullType":"datetime","canBeNull":1,"type":"datetime","description":"the date when the task finished","readOnly":1}}},"dedicated.storage.TaskFunctionEnum":{"namespace":"dedicated.storage","enum":["backupRecursiveDestroy","clusterLeclercAclUpdate","clusterLeclercChangeServiceIp","clusterLeclercDeleteSnapshotDirectory","clusterLeclercDestroyNasContainer","clusterLeclercPartitionAdd","clusterLeclercPartitionDelete","clusterLeclercPartitionUpdate","clusterLeclercQuotaUpdate","clusterLeclercSetupNasContainer","clusterLeclercSnapshotUpdate","nasAclUpdate","nasDeleteSnapshotDirectory","nasPartitionAdd","nasPartitionDelete","nasPartitionUpdate","nasQuotaUpdate","remoteBackupRecursiveDestroy"],"id":"TaskFunctionEnum","enumType":"string","description":"Distincts task"},"dedicated.nasha.Snapshot":{"namespace":"dedicated.nasha","id":"Snapshot","description":"Partition Snapshot","properties":{"snapshotType":{"fullType":"dedicated.storage.SnapshotEnum","canBeNull":0,"type":"dedicated.storage.SnapshotEnum","description":"the interval of snapshot","readOnly":1}}},"service.RenewType":{"namespace":"service","id":"RenewType","description":"Map a possible renew for a specific service","properties":{"period":{"canBeNull":1,"type":"long","description":"period of renew in month"},"forced":{"canBeNull":0,"type":"boolean","description":"The service forced to be renewed"},"automatic":{"canBeNull":0,"type":"boolean","description":"The service is automatically renewed"},"deleteAtExpiration":{"canBeNull":0,"type":"boolean","description":"The service will be deleted at expiration"}}},"services.Service":{"namespace":"services","id":"Service","description":"Details about a Service","properties":{"status":{"fullType":"service.StateEnum","canBeNull":0,"type":"service.StateEnum","description":null,"readOnly":1},"engagedUpTo":{"fullType":"date","canBeNull":1,"type":"date","description":null,"readOnly":1},"possibleRenewPeriod":{"fullType":"long[]","canBeNull":1,"type":"long[]","description":"All the possible renew period of your service in month","readOnly":1},"contactBilling":{"fullType":"coreTypes.AccountId:string","canBeNull":0,"type":"string","description":null,"readOnly":1},"renew":{"fullType":"service.RenewType","canBeNull":1,"type":"service.RenewType","description":"Way of handling the renew","readOnly":0},"domain":{"fullType":"string","canBeNull":0,"type":"string","description":null,"readOnly":1},"expiration":{"fullType":"date","canBeNull":0,"type":"date","description":null,"readOnly":1},"contactTech":{"fullType":"coreTypes.AccountId:string","canBeNull":0,"type":"string","description":null,"readOnly":1},"contactAdmin":{"fullType":"coreTypes.AccountId:string","canBeNull":0,"type":"string","description":null,"readOnly":1},"creation":{"fullType":"date","canBeNull":0,"type":"date","description":null,"readOnly":1}}},"dedicated.nasha.Vrack":{"namespace":"dedicated.nasha","id":"Vrack","description":"Partition Vrack","properties":{"vrackName":{"fullType":"string","canBeNull":0,"type":"string","description":"vrack name","readOnly":1},"id":{"fullType":"long","canBeNull":0,"type":"long","description":"ID","readOnly":1},"serviceIp":{"fullType":"ipInterface","canBeNull":0,"type":"ipInterface","description":"service ip","readOnly":1},"type":{"fullType":"string","canBeNull":0,"type":"string","description":"type of","readOnly":1}}},"dedicated.nasha.Quota":{"namespace":"dedicated.nasha","id":"Quota","description":"Partition Quota","properties":{"uid":{"fullType":"long","canBeNull":0,"type":"long","description":"the uid to set quota on","readOnly":1},"size":{"fullType":"long","canBeNull":0,"type":"long","description":"the size to set in MB","readOnly":1}}},"service.StateEnum":{"namespace":"service","enum":["expired","inCreation","ok","unPaid"],"id":"StateEnum","enumType":"string","description":""},"dedicated.TaskStatusEnum":{"namespace":"dedicated","enum":["cancelled","customerError","doing","done","init","ovhError","todo"],"id":"TaskStatusEnum","enumType":"string","description":"different task status"}},"apiVersion":"1.0","resourcePath":"/dedicated/nasha","apis":[{"operations":[{"parameters":[{"required":1,"dataType":"string","paramType":"path","name":"serviceName","description":"The internal name of your storage"}],"httpMethod":"GET","apiStatus":{"value":"BETA","description":"Beta version"},"noAuthentication":0,"description":"Get this object properties","responseType":"services.Service"},{"parameters":[{"required":1,"dataType":"services.Service","paramType":"body","description":"New object properties"},{"required":1,"dataType":"string","paramType":"path","name":"serviceName","description":"The internal name of your storage"}],"httpMethod":"PUT","apiStatus":{"value":"BETA","description":"Beta version"},"noAuthentication":0,"description":"Alter this object properties","responseType":"void"}],"path":"/dedicated/nasha/{serviceName}/serviceInfos","description":"Details about a Service"},{"operations":[{"parameters":[{"required":1,"dataType":"string","paramType":"path","name":"serviceName","description":"The internal name of your storage"}],"httpMethod":"DELETE","apiStatus":{"value":"BETA","description":"Beta version"},"noAuthentication":0,"description":"Delete the vrack container","responseType":"dedicated.nasTask.Task"}],"path":"/dedicated/nasha/{serviceName}/vrack","description":"Partition Vrack"},{"operations":[{"parameters":[{"required":1,"dataType":"string","paramType":"path","name":"serviceName","description":"The internal name of your storage"}],"httpMethod":"GET","apiStatus":{"value":"BETA","description":"Beta version"},"noAuthentication":0,"description":"Get this object properties","responseType":"dedicated.nasha.Storage"},{"parameters":[{"required":1,"dataType":"dedicated.nasha.Storage","paramType":"body","description":"New object properties"},{"required":1,"dataType":"string","paramType":"path","name":"serviceName","description":"The internal name of your storage"}],"httpMethod":"PUT","apiStatus":{"value":"BETA","description":"Beta version"},"noAuthentication":0,"description":"Alter this object properties","responseType":"void"}],"path":"/dedicated/nasha/{serviceName}","description":"Storage nas HA"},{"operations":[{"parameters":[{"required":0,"dataType":"dedicated.TaskStatusEnum","paramType":"query","name":"status","description":"Filter the value of status property (=)"},{"required":0,"dataType":"dedicated.storage.TaskFunctionEnum","paramType":"query","name":"operation","description":"Filter the value of operation property (=)"},{"required":1,"dataType":"string","paramType":"path","name":"serviceName","description":"The internal name of your storage"}],"httpMethod":"GET","apiStatus":{"value":"BETA","description":"Beta version"},"noAuthentication":0,"description":"View task list","responseType":"long[]"}],"path":"/dedicated/nasha/{serviceName}/task","description":"List the dedicated.nasTask.Task objects"},{"operations":[{"parameters":[{"required":1,"dataType":"string","paramType":"path","name":"serviceName","description":"The internal name of your storage"},{"required":1,"dataType":"long","paramType":"path","name":"taskId","description":"id of the task"}],"httpMethod":"GET","apiStatus":{"value":"BETA","description":"Beta version"},"noAuthentication":0,"description":"Get this object properties","responseType":"dedicated.nasTask.Task"}],"path":"/dedicated/nasha/{serviceName}/task/{taskId}","description":"Storage task"},{"operations":[{"parameters":[{"required":1,"dataType":"string","paramType":"path","name":"serviceName","description":"The internal name of your storage"}],"httpMethod":"GET","apiStatus":{"value":"BETA","description":"Beta version"},"noAuthentication":0,"description":"Get partition list","responseType":"string[]"},{"parameters":[{"required":1,"dataType":"dedicated.storage.ProtocolEnum","paramType":"body","name":"protocol","description":"NFS|CIFS|NFS_CIFS"},{"required":1,"dataType":"string","paramType":"body","name":"partitionName","description":"Partition name"},{"required":1,"dataType":"long","paramType":"body","name":"size","description":"Partition size"},{"required":1,"dataType":"string","paramType":"path","name":"serviceName","description":"The internal name of your storage"}],"httpMethod":"POST","apiStatus":{"value":"BETA","description":"Beta version"},"noAuthentication":0,"description":"Create a new partition","responseType":"dedicated.nasTask.Task"}],"path":"/dedicated/nasha/{serviceName}/partition","description":"List the dedicated.nasha.Partition objects"},{"operations":[{"parameters":[{"required":1,"dataType":"string","paramType":"path","name":"serviceName","description":"The internal name of your storage"},{"required":1,"dataType":"string","paramType":"path","name":"partitionName","description":"the given name of partition"}],"httpMethod":"GET","apiStatus":{"value":"BETA","description":"Beta version"},"noAuthentication":0,"description":"Get quota for this partition","responseType":"long[]"},{"parameters":[{"required":1,"dataType":"long","paramType":"body","name":"uid","description":"the uid to set quota on"},{"required":1,"dataType":"long","paramType":"body","name":"size","description":"the size to set in MB"},{"required":1,"dataType":"string","paramType":"path","name":"serviceName","description":"The internal name of your storage"},{"required":1,"dataType":"string","paramType":"path","name":"partitionName","description":"the given name of partition"}],"httpMethod":"POST","apiStatus":{"value":"BETA","description":"Beta version"},"noAuthentication":0,"description":"Set a new quota","responseType":"dedicated.nasTask.Task"}],"path":"/dedicated/nasha/{serviceName}/partition/{partitionName}/quota","description":"List the dedicated.nasha.Quota objects"},{"operations":[{"parameters":[{"required":1,"dataType":"string","paramType":"path","name":"serviceName","description":"The internal name of your storage"},{"required":1,"dataType":"string","paramType":"path","name":"partitionName","description":"the given name of partition"},{"required":1,"dataType":"long","paramType":"path","name":"uid","description":"the uid to set quota on"}],"httpMethod":"GET","apiStatus":{"value":"BETA","description":"Beta version"},"noAuthentication":0,"description":"Get this object properties","responseType":"dedicated.nasha.Quota"},{"parameters":[{"required":1,"dataType":"string","paramType":"path","name":"serviceName","description":"The internal name of your storage"},{"required":1,"dataType":"string","paramType":"path","name":"partitionName","description":"the given name of partition"},{"required":1,"dataType":"long","paramType":"path","name":"uid","description":"the uid to set quota on"}],"httpMethod":"DELETE","apiStatus":{"value":"BETA","description":"Beta version"},"noAuthentication":0,"description":"Delete a given quota","responseType":"dedicated.nasTask.Task"}],"path":"/dedicated/nasha/{serviceName}/partition/{partitionName}/quota/{uid}","description":"Partition Quota"},{"operations":[{"parameters":[{"required":1,"dataType":"string","paramType":"path","name":"serviceName","description":"The internal name of your storage"},{"required":1,"dataType":"string","paramType":"path","name":"partitionName","description":"the given name of partition"}],"httpMethod":"GET","apiStatus":{"value":"BETA","description":"Beta version"},"noAuthentication":0,"description":"Get this object properties","responseType":"dedicated.nasha.Partition"},{"parameters":[{"required":1,"dataType":"dedicated.nasha.Partition","paramType":"body","description":"New object properties"},{"required":1,"dataType":"string","paramType":"path","name":"serviceName","description":"The internal name of your storage"},{"required":1,"dataType":"string","paramType":"path","name":"partitionName","description":"the given name of partition"}],"httpMethod":"PUT","apiStatus":{"value":"BETA","description":"Beta version"},"noAuthentication":0,"description":"Alter this object properties","responseType":"void"},{"parameters":[{"required":1,"dataType":"string","paramType":"path","name":"serviceName","description":"The internal name of your storage"},{"required":1,"dataType":"string","paramType":"path","name":"partitionName","description":"the given name of partition"}],"httpMethod":"DELETE","apiStatus":{"value":"BETA","description":"Beta version"},"noAuthentication":0,"description":"Delete this partition","responseType":"dedicated.nasTask.Task"}],"path":"/dedicated/nasha/{serviceName}/partition/{partitionName}","description":"Storage zpool partition"},{"operations":[{"parameters":[{"required":1,"dataType":"string","paramType":"path","name":"serviceName","description":"The internal name of your storage"},{"required":1,"dataType":"string","paramType":"path","name":"partitionName","description":"the given name of partition"}],"httpMethod":"GET","apiStatus":{"value":"BETA","description":"Beta version"},"noAuthentication":0,"description":"Get all RIPE/ARIN blocks that can be used in the ACL","responseType":"ipBlock[]"}],"path":"/dedicated/nasha/{serviceName}/partition/{partitionName}/authorizableBlocks","description":"authorizableBlocks operations"},{"operations":[{"parameters":[{"required":1,"dataType":"string","paramType":"path","name":"serviceName","description":"The internal name of your storage"},{"required":1,"dataType":"string","paramType":"path","name":"partitionName","description":"the given name of partition"}],"httpMethod":"GET","apiStatus":{"value":"BETA","description":"Beta version"},"noAuthentication":0,"description":"Get all IPs that can be used in the ACL","responseType":"ip[]"}],"path":"/dedicated/nasha/{serviceName}/partition/{partitionName}/authorizableIps","description":"authorizableIps operations"},{"operations":[{"parameters":[{"required":1,"dataType":"string","paramType":"path","name":"serviceName","description":"The internal name of your storage"},{"required":1,"dataType":"string","paramType":"path","name":"partitionName","description":"the given name of partition"}],"httpMethod":"GET","apiStatus":{"value":"BETA","description":"Beta version"},"noAuthentication":0,"description":"get ACL for this partition","responseType":"ipBlock[]"},{"parameters":[{"required":1,"dataType":"ipBlock","paramType":"body","name":"ip","description":"Ip or block to add"},{"required":1,"dataType":"string","paramType":"path","name":"serviceName","description":"The internal name of your storage"},{"required":1,"dataType":"string","paramType":"path","name":"partitionName","description":"the given name of partition"}],"httpMethod":"POST","apiStatus":{"value":"BETA","description":"Beta version"},"noAuthentication":0,"description":"Add a new ACL entry","responseType":"dedicated.nasTask.Task"}],"path":"/dedicated/nasha/{serviceName}/partition/{partitionName}/access","description":"List the dedicated.nasha.Access objects"},{"operations":[{"parameters":[{"required":1,"dataType":"string","paramType":"path","name":"serviceName","description":"The internal name of your storage"},{"required":1,"dataType":"string","paramType":"path","name":"partitionName","description":"the given name of partition"},{"required":1,"dataType":"ipBlock","paramType":"path","name":"ip","description":"the ip in root on storage"}],"httpMethod":"GET","apiStatus":{"value":"BETA","description":"Beta version"},"noAuthentication":0,"description":"Get this object properties","responseType":"dedicated.nasha.Access"},{"parameters":[{"required":1,"dataType":"string","paramType":"path","name":"serviceName","description":"The internal name of your storage"},{"required":1,"dataType":"string","paramType":"path","name":"partitionName","description":"the given name of partition"},{"required":1,"dataType":"ipBlock","paramType":"path","name":"ip","description":"the ip in root on storage"}],"httpMethod":"DELETE","apiStatus":{"value":"BETA","description":"Beta version"},"noAuthentication":0,"description":"Delete an ACL entry","responseType":"dedicated.nasTask.Task"}],"path":"/dedicated/nasha/{serviceName}/partition/{partitionName}/access/{ip}","description":"Define Acl for partition"},{"operations":[{"parameters":[{"required":1,"dataType":"string","paramType":"path","name":"serviceName","description":"The internal name of your storage"},{"required":1,"dataType":"string","paramType":"path","name":"partitionName","description":"the given name of partition"}],"httpMethod":"GET","apiStatus":{"value":"BETA","description":"Beta version"},"noAuthentication":0,"description":"Get scheduled snapshot types for this partition","responseType":"dedicated.storage.SnapshotEnum[]"},{"parameters":[{"required":1,"dataType":"dedicated.storage.SnapshotEnum","paramType":"body","name":"snapshotType","description":"Snapshot interval to add"},{"required":1,"dataType":"string","paramType":"path","name":"serviceName","description":"The internal name of your storage"},{"required":1,"dataType":"string","paramType":"path","name":"partitionName","description":"the given name of partition"}],"httpMethod":"POST","apiStatus":{"value":"BETA","description":"Beta version"},"noAuthentication":0,"description":"Schedule a new snapshot type","responseType":"dedicated.nasTask.Task"}],"path":"/dedicated/nasha/{serviceName}/partition/{partitionName}/snapshot","description":"List the dedicated.nasha.Snapshot objects"},{"operations":[{"parameters":[{"required":1,"dataType":"string","paramType":"path","name":"serviceName","description":"The internal name of your storage"},{"required":1,"dataType":"string","paramType":"path","name":"partitionName","description":"the given name of partition"},{"required":1,"dataType":"dedicated.storage.SnapshotEnum","paramType":"path","name":"snapshotType","description":"the interval of snapshot"}],"httpMethod":"GET","apiStatus":{"value":"BETA","description":"Beta version"},"noAuthentication":0,"description":"Get this object properties","responseType":"dedicated.nasha.Snapshot"},{"parameters":[{"required":1,"dataType":"string","paramType":"path","name":"serviceName","description":"The internal name of your storage"},{"required":1,"dataType":"string","paramType":"path","name":"partitionName","description":"the given name of partition"},{"required":1,"dataType":"dedicated.storage.SnapshotEnum","paramType":"path","name":"snapshotType","description":"the interval of snapshot"}],"httpMethod":"DELETE","apiStatus":{"value":"BETA","description":"Beta version"},"noAuthentication":0,"description":"Delete a given snapshot","responseType":"dedicated.nasTask.Task"}],"path":"/dedicated/nasha/{serviceName}/partition/{partitionName}/snapshot/{snapshotType}","description":"Partition Snapshot"},{"operations":[{"parameters":[],"httpMethod":"GET","apiStatus":{"value":"BETA","description":"Beta version"},"noAuthentication":0,"description":"List available services","responseType":"string[]"}],"path":"/dedicated/nasha","description":"Operations about the STORAGE service"}],"basePath":"https://api.ovh.com/1.0"}